drf_queryset/__init__.py
drf_queryset/mixins.py
drf_queryset-0.1.0.dist-info/LICENSE
drf_queryset-0.1.0.dist-info/METADATA
drf_queryset-0.1.0.dist-info/WHEEL
drf_queryset-0.1.0.dist-info/top_level.txt
drf_queryset-0.1.0.dist-info/RECORD
